baechu805_cli/__init__.py
baechu805_cli/cli.py
baechu805_cli-0.1.1.dist-info/METADATA
baechu805_cli-0.1.1.dist-info/WHEEL
baechu805_cli-0.1.1.dist-info/entry_points.txt
baechu805_cli-0.1.1.dist-info/top_level.txt
baechu805_cli-0.1.1.dist-info/RECORD
