Metadata-Version: 2.1
Name: baechu805_cli
Version: 0.1.1
Summary: Default template for PDM package
Author-email: baechu805 <bjoo606@naver.com>
License: MIT
Requires-Python: >=3.9
Requires-Dist: baechu805-lotto >=0.2.0
